Khach_Khach/__init__.py
Khach_Khach/bounding_box_processor.py
Khach_Khach/detectannotate.py
Khach_Khach/extended_array_processor.py
Khach_Khach/file_appender.py
Khach_Khach/frame_extractor.py
Khach_Khach/keypoint_annotater.py
Khach_Khach/khach_khach.py
Khach_Khach/xyn_extractor.py
khach_khach2.0-0.5.dist-info/METADATA
khach_khach2.0-0.5.dist-info/WHEEL
khach_khach2.0-0.5.dist-info/top_level.txt
khach_khach2.0-0.5.dist-info/RECORD
