Metadata-Version: 2.1
Name: khach-khach2.0
Version: 0.5
Summary: A package for processing video frames, annotating keypoints, and more.
Home-page: https://github.com/pratapsdev11/Khach_Khach/tree/main
Author: pratapdevs11
Author-email: divyapratap360@gmail.com
Classifier: Programming Language :: Python :: 3
Classifier: License :: OSI Approved :: MIT License
Classifier: Operating System :: OS Independent
Requires-Python: >=3.6
Requires-Dist: opencv-python
Requires-Dist: numpy
Requires-Dist: ultralytics
